adecty_design/__init__.py
adecty_design/adecty_design.py
adecty_design/elements/__init__.py
adecty_design/elements/colors.py
adecty_design/elements/config.py
adecty_design/elements/fonts.py
adecty_design/elements/footer.py
adecty_design/elements/form.py
adecty_design/elements/header.py
adecty_design/elements/header_navigation_item.py
adecty_design/elements/input.py
adecty_design/elements/page.py
adecty_design/elements/screen.py
adecty_design/elements/table.py
adecty_design/elements/text.py
adecty_design/markups/__init__.py
adecty_design/markups/markups.py
adecty_design/markups/css/base.css
adecty_design/markups/css/footer.css
adecty_design/markups/css/header.css
adecty_design/markups/css/table.css
adecty_design/markups/html/base.html
adecty_design/markups/html/footer.html
adecty_design/markups/html/form.html
adecty_design/markups/html/header.html
adecty_design/markups/html/header_navigation_item.html
adecty_design/markups/html/page.html
adecty_design/markups/html/screen.html
adecty_design/markups/html/text.html
build/lib/adecty_design/__init__.py
build/lib/adecty_design/adecty_design.py
build/lib/adecty_design/elements/__init__.py
build/lib/adecty_design/elements/colors.py
build/lib/adecty_design/elements/config.py
build/lib/adecty_design/elements/fonts.py
build/lib/adecty_design/elements/footer.py
build/lib/adecty_design/elements/form.py
build/lib/adecty_design/elements/header.py
build/lib/adecty_design/elements/header_navigation_item.py
build/lib/adecty_design/elements/input.py
build/lib/adecty_design/elements/page.py
build/lib/adecty_design/elements/screen.py
build/lib/adecty_design/elements/table.py
build/lib/adecty_design/elements/text.py
build/lib/adecty_design/markups/__init__.py
build/lib/adecty_design/markups/markups.py
adecty_design-0.1.0.dist-info/LICENSE
adecty_design-0.1.0.dist-info/METADATA
adecty_design-0.1.0.dist-info/WHEEL
adecty_design-0.1.0.dist-info/top_level.txt
adecty_design-0.1.0.dist-info/RECORD
