Metadata-Version: 2.1
Name: adecty-design
Version: 0.1.0
Summary: Module with which you can greatly simplify the development of the UI
Home-page: https://design.adecty.com
Author: Yegor Yakubovich
Author-email: personal@yegoryakubovich.com
License: Apache 2.0
Classifier: Intended Audience :: Developers
Classifier: License :: OSI Approved :: Apache Software License
Classifier: Programming Language :: Python
Classifier: Operating System :: OS Independent
Requires-Python: >=3.7
License-File: LICENSE
